pysmartdatamodels/LICENSE.txt
pysmartdatamodels/README.md
pysmartdatamodels/__init__.py
pysmartdatamodels/changes_log.md
pysmartdatamodels/model-assets/datamodels_metadata.json
pysmartdatamodels/model-assets/official_list_data_models.json
pysmartdatamodels/model-assets/smartdatamodels.json
pysmartdatamodels/my_subject/CONTRIBUTORS.yaml
pysmartdatamodels/my_subject/TODO
pysmartdatamodels/my_subject/my_datamodel/ADOPTERS.yaml
pysmartdatamodels/my_subject/my_datamodel/examples/example-normalized.json
pysmartdatamodels/my_subject/my_datamodel/examples/example-normalized.jsonld
pysmartdatamodels/my_subject/my_datamodel/examples/example.json
pysmartdatamodels/my_subject/my_datamodel/examples/example.jsonld
pysmartdatamodels/my_subject/my_datamodel/notes.yaml
pysmartdatamodels/my_subject/notes.yaml
pysmartdatamodels/pysmartdatamodels.py
pysmartdatamodels/utils/__init__.py
pysmartdatamodels/utils/common_utils.py
pysmartdatamodels-0.8.0.2.dist-info/METADATA
pysmartdatamodels-0.8.0.2.dist-info/WHEEL
pysmartdatamodels-0.8.0.2.dist-info/RECORD
