Metadata-Version: 2.1
Name: pysmartdatamodels
Version: 0.8.0.2
Summary: Open-licensed and free data models to model your digital twins, share data in data spaces or develop smart applications
Home-page: https://github.com/smart-data-models/data-models/tree/master/pysmartdatamodels
Author: aabella
Author-email: alberto.abella@fiware.org
Requires-Python: >=3.8,<4.0
Classifier: Development Status :: 4 - Beta
Classifier: Intended Audience :: Developers
Classifier: License :: OSI Approved :: MIT License
Classifier: Operating System :: OS Independent
Classifier: Programming Language :: Python
Classifier: Programming Language :: Python :: 3
Classifier: Programming Language :: Python :: 3.8
Classifier: Programming Language :: Python :: 3.9
Classifier: Programming Language :: Python :: 3.10
Classifier: Programming Language :: Python :: 3.11
Classifier: Programming Language :: Python :: 3.12
Requires-Dist: Faker (>=18.10.1)
Requires-Dist: fuzzywuzzy (>=0.18)
Requires-Dist: jsonref (>=1.0.0)
Requires-Dist: jsonschema (>=4.17.3,<5.0.0)
Requires-Dist: python-Levenshtein (>=0.25)
Requires-Dist: pytz (>=2022.7.1)
Requires-Dist: requests (>=2.28.2,<3.0.0)
Requires-Dist: rstr (>=3.2.1,<4.0.0)
Requires-Dist: ruamel.yaml (>=0.18.1)
Requires-Dist: urllib3 (>=2.0.7,<3.0.0)
Requires-Dist: validator-collection (>=1.5.0,<2.0.0)
Project-URL: Repository, https://github.com/smart-data-models/data-models/tree/master/pysmartdatamodels
